Workbook

Sheet 前提条件
B1: Kaizen AI 初年度収益シミュレーション — 前提条件
B2: 凡例: 青字＝入力セル（自由に変更可） / 黄色塗り＝特に重要なレバー / 黒字＝数式（変更しない）
B3: ※ 全て仮置きの前提です。実績が出たら随時更新してください。金額は万円・税抜。件数は期待値（小数）で計算します。
B5: 1. 営業活動（シナリオ別）
C6: 保守 | D6: 標準 | E6: 強気
B7: 月間の無料相談件数（フル稼働時・件/月） | C7: 2 | D7: 4 | E7: 6 | F7: 知人紹介・問い合わせから獲得できる相談数。最重要レバー
B8: 相談 → 業務診断 の転換率 | C8: 0.3 | D8: 0.4 | E8: 0.5 | F8: 無料相談のうち有償診断に進む割合
B9: 診断 → プロジェクト の転換率 | C9: 0.4 | D9: 0.5 | E9: 0.6 | F9: 診断実施後にプロジェクト受注に至る割合（翌月受注と仮定）
B10: プロジェクト → 顧問契約 の転換率 | C10: 0.3 | D10: 0.4 | E10: 0.5 | F10: プロジェクト完了後に顧問契約へ移行する割合（翌月開始と仮定）
B11: 顧問契約の月次解約率 | C11: 0.05 | D11: 0.03 | E11: 0.02 | F11: 稼働中の顧問契約が1ヶ月に解約される割合
B12: 研修・ワークショップ実施回数（回/四半期） | C12: 0 | D12: 1 | E12: 2 | F12: 3・6・9・12ヶ月目に計上
B14: 2. 立ち上がり係数（共通）
B15: 1〜3ヶ月目（フル稼働比） | C15: 0.5 | F15: 設立直後は営業基盤づくりに時間を要する想定
B16: 4〜6ヶ月目（フル稼働比） | C16: 0.75
B17: 7〜12ヶ月目（フル稼働比） | C17: 1
B19: 3. 単価（共通・万円・税抜）
B20: 業務診断 単価（万円/件） | C20: 40 | F20: サービスカタログのレンジ 20〜80万円の中央付近を仮置き
B21: プロジェクト 単価（万円/件） | C21: 80 | F21: レンジ 30〜300万円。立ち上げ期は小型案件中心を想定
B22: 顧問契約 月額（万円/月） | C22: 20 | F22: レンジ 月15〜50万円の下限寄りを仮置き
B23: 研修・ワークショップ 単価（万円/回） | C23: 25 | F23: レンジ 10〜50万円
B25: 4. コスト（共通・万円/月）
B26: AIツール・API利用料（万円/月） | C26: 3 | F26: Claude API・各種SaaS等
B27: その他固定経費（万円/月） | C27: 7 | F27: 会計ソフト・通信・交通・雑費等。役員報酬は含まない
B28: 変動費率（売上比） | C28: 0.05 | F28: 案件遂行に伴う実費（外部ツール・出張等）の概算
B30: 注: 役員報酬・税金は含まない「営業ベース」の簡易モデルです。法人設立費用等の一時コストも別途。

Sheet 月次_保守
A1: 月次計画 — 保守シナリオ（金額: 万円・税抜 / 件数: 期待値）
A3: 月 | B3: 1月目 | C3: 2月目 | D3: 3月目 | E3: 4月目 | F3: 5月目 | G3: 6月目 | H3: 7月目 | I3: 8月目 | J3: 9月目 | K3: 10月目 | L3: 11月目 | M3: 12月目 | N3: 年間
A4: 無料相談件数（件） | B4: =前提条件!$C$7*前提条件!$C$15 -> 1 | C4: =前提条件!$C$7*前提条件!$C$15 -> 1 | D4: =前提条件!$C$7*前提条件!$C$15 -> 1 | E4: =前提条件!$C$7*前提条件!$C$16 -> 1.5 | F4: =前提条件!$C$7*前提条件!$C$16 -> 1.5 | G4: =前提条件!$C$7*前提条件!$C$16 -> 1.5 | H4: =前提条件!$C$7*前提条件!$C$17 -> 2 | I4: =前提条件!$C$7*前提条件!$C$17 -> 2 | J4: =前提条件!$C$7*前提条件!$C$17 -> 2 | K4: =前提条件!$C$7*前提条件!$C$17 -> 2 | L4: =前提条件!$C$7*前提条件!$C$17 -> 2 | M4: =前提条件!$C$7*前提条件!$C$17 -> 2 | N4: =SUM(B4:M4) -> 19.5
A5: 業務診断 件数（件） | B5: =B4*前提条件!$C$8 -> 0.3 | C5: =C4*前提条件!$C$8 -> 0.3 | D5: =D4*前提条件!$C$8 -> 0.3 | E5: =E4*前提条件!$C$8 -> 0.45 | F5: =F4*前提条件!$C$8 -> 0.45 | G5: =G4*前提条件!$C$8 -> 0.45 | H5: =H4*前提条件!$C$8 -> 0.6 | I5: =I4*前提条件!$C$8 -> 0.6 | ... M5: =M4*前提条件!$C$8 -> 0.6 | N5: =SUM(B5:M5) -> 5.85
A6: プロジェクト 件数（件） | B6: 0 | C6: =B5*前提条件!$C$9 -> 0.12 | D6: =C5*前提条件!$C$9 -> 0.12 | E6: =D5*前提条件!$C$9 -> 0.12 | F6: =E5*前提条件!$C$9 -> 0.18 | G6: =F5*前提条件!$C$9 -> 0.18 | H6: =G5*前提条件!$C$9 -> 0.18 | I6: =H5*前提条件!$C$9 -> 0.24 | J6: =I5*前提条件!$C$9 -> 0.24 | ... M6: =L5*前提条件!$C$9 -> 0.24 | N6: =SUM(B6:M6) -> 2.1
A7: 顧問 新規獲得（件） | B7: 0 | C7: =B6*前提条件!$C$10 -> 0 | D7: =C6*前提条件!$C$10 -> 0.036 | E7: =D6*前提条件!$C$10 -> 0.036 | F7: =E6*前提条件!$C$10 -> 0.036 | G7: =F6*前提条件!$C$10 -> 0.054 | H7: =G6*前提条件!$C$10 -> 0.054 | I7: =H6*前提条件!$C$10 -> 0.054 | J7: =I6*前提条件!$C$10 -> 0.072 | ... M7: =L6*前提条件!$C$10 -> 0.072 | N7: =SUM(B7:M7) -> 0.558
A8: 顧問 稼働数（件・月末） | B8: =B7 -> 0 | C8: =B8*(1-前提条件!$C$11)+C7 -> 0 | D8: =C8*(1-前提条件!$C$11)+D7 -> 0.036 | E8: =D8*(1-前提条件!$C$11)+E7 -> 0.0702 | F8: =E8*(1-前提条件!$C$11)+F7 -> 0.10269 | G8: =F8*(1-前提条件!$C$11)+G7 -> 0.1515555 | H8: =G8*(1-前提条件!$C$11)+H7 -> 0.19797772 | I8: =H8*(1-前提条件!$C$11)+I7 -> 0.24207884 | J8: =I8*(1-前提条件!$C$11)+J7 -> 0.3019749 | ... M8: =L8*(1-前提条件!$C$11)+M7 -> 0.46428573 | N8: =M8 -> 0.46428573
A9: 研修 実施回数（回） | B9: 0 | C9: 0 | D9: =前提条件!$C$12 -> 0 | E9: 0 | F9: 0 | G9: =前提条件!$C$12 -> 0 | H9: 0 | I9: 0 | J9: =前提条件!$C$12 -> 0 | K9: 0 | L9: 0 | M9: =前提条件!$C$12 -> 0 | N9: =SUM(B9:M9) -> 0
A10: 売上（万円）
A11: 業務診断 | B11: =B5*前提条件!$C$20 -> 12 | C11: =C5*前提条件!$C$20 -> 12 | D11: =D5*前提条件!$C$20 -> 12 | E11: =E5*前提条件!$C$20 -> 18 | F11: =F5*前提条件!$C$20 -> 18 | G11: =G5*前提条件!$C$20 -> 18 | H11: =H5*前提条件!$C$20 -> 24 | I11: =I5*前提条件!$C$20 -> 24 | ... M11: =M5*前提条件!$C$20 -> 24 | N11: =SUM(B11:M11) -> 234
A12: プロジェクト | B12: =B6*前提条件!$C$21 -> 0 | C12: =C6*前提条件!$C$21 -> 9.6 | D12: =D6*前提条件!$C$21 -> 9.6 | E12: =E6*前提条件!$C$21 -> 9.6 | F12: =F6*前提条件!$C$21 -> 14.4 | G12: =G6*前提条件!$C$21 -> 14.4 | H12: =H6*前提条件!$C$21 -> 14.4 | I12: =I6*前提条件!$C$21 -> 19.2 | ... M12: =M6*前提条件!$C$21 -> 19.2 | N12: =SUM(B12:M12) -> 168
A13: 顧問契約 | B13: =B8*前提条件!$C$22 -> 0 | C13: =C8*前提条件!$C$22 -> 0 | D13: =D8*前提条件!$C$22 -> 0.72 | E13: =E8*前提条件!$C$22 -> 1.404 | F13: =F8*前提条件!$C$22 -> 2.0538 | G13: =G8*前提条件!$C$22 -> 3.03111 | H13: =H8*前提条件!$C$22 -> 3.9595545 | I13: =I8*前提条件!$C$22 -> 4.8415768 | ... M13: =M8*前提条件!$C$22 -> 9.2857145 | N13: =SUM(B13:M13) -> 46.771424
A14: 研修 | B14: =B9*前提条件!$C$23 -> 0 | C14: =C9*前提条件!$C$23 -> 0 | D14: =D9*前提条件!$C$23 -> 0 | E14: =E9*前提条件!$C$23 -> 0 | F14: =F9*前提条件!$C$23 -> 0 | G14: =G9*前提条件!$C$23 -> 0 | H14: =H9*前提条件!$C$23 -> 0 | I14: =I9*前提条件!$C$23 -> 0 | ... M14: =M9*前提条件!$C$23 -> 0 | N14: =SUM(B14:M14) -> 0
A15: 売上合計 | B15: =SUM(B11:B14) -> 12 | C15: =SUM(C11:C14) -> 21.6 | D15: =SUM(D11:D14) -> 22.32 | E15: =SUM(E11:E14) -> 29.004 | F15: =SUM(F11:F14) -> 34.4538 | G15: =SUM(G11:G14) -> 35.43111 | H15: =SUM(H11:H14) -> 42.359555 | I15: =SUM(I11:I14) -> 48.041577 | ... M15: =SUM(M11:M14) -> 52.485715 | N15: =SUM(B15:M15) -> 448.77142
A16: コスト（万円）
A17: 固定費（ツール＋経費） | B17: =前提条件!$C$26+前提条件!$C$27 -> 10 | C17: =前提条件!$C$26+前提条件!$C$27 -> 10 | D17: =前提条件!$C$26+前提条件!$C$27 -> 10 | E17: =前提条件!$C$26+前提条件!$C$27 -> 10 | F17: =前提条件!$C$26+前提条件!$C$27 -> 10 | G17: =前提条件!$C$26+前提条件!$C$27 -> 10 | H17: =前提条件!$C$26+前提条件!$C$27 -> 10 | I17: =前提条件!$C$26+前提条件!$C$27 -> 10 | ... M17: =前提条件!$C$26+前提条件!$C$27 -> 10 | N17: =SUM(B17:M17) -> 120
A18: 変動費 | B18: =B15*前提条件!$C$28 -> 0.6 | C18: =C15*前提条件!$C$28 -> 1.08 | D18: =D15*前提条件!$C$28 -> 1.116 | E18: =E15*前提条件!$C$28 -> 1.4502 | F18: =F15*前提条件!$C$28 -> 1.72269 | G18: =G15*前提条件!$C$28 -> 1.7715555 | H18: =H15*前提条件!$C$28 -> 2.1179777 | I18: =I15*前提条件!$C$28 -> 2.4020788 | ... M18: =M15*前提条件!$C$28 -> 2.6242857 | N18: =SUM(B18:M18) -> 22.438571
A19: コスト合計 | B19: =B17+B18 -> 10.6 | C19: =C17+C18 -> 11.08 | D19: =D17+D18 -> 11.116 | E19: =E17+E18 -> 11.4502 | F19: =F17+F18 -> 11.72269 | G19: =G17+G18 -> 11.771555 | H19: =H17+H18 -> 12.117978 | I19: =I17+I18 -> 12.402079 | ... M19: =M17+M18 -> 12.624286 | N19: =SUM(B19:M19) -> 142.43857
A20: 営業利益 | B20: =B15-B19 -> 1.4 | C20: =C15-C19 -> 10.52 | D20: =D15-D19 -> 11.204 | E20: =E15-E19 -> 17.5538 | F20: =F15-F19 -> 22.73111 | G20: =G15-G19 -> 23.659554 | H20: =H15-H19 -> 30.241577 | I20: =I15-I19 -> 35.639498 | ... M20: =M15-M19 -> 39.861429 | N20: =SUM(B20:M20) -> 306.33285
A21: 累計営業利益 | B21: =B20 -> 1.4 | C21: =B21+C20 -> 11.92 | D21: =C21+D20 -> 23.124 | E21: =D21+E20 -> 40.6778 | F21: =E21+F20 -> 63.40891 | G21: =F21+G20 -> 87.068465 | H21: =G21+H20 -> 117.31004 | I21: =H21+I20 -> 152.94954 | J21: =I21+J20 -> 189.72706 | ... M21: =L21+M20 -> 306.33285 | N21: =M21 -> 306.33285

Sheet 月次_標準
A1: 月次計画 — 標準シナリオ（金額: 万円・税抜 / 件数: 期待値）
A3: 月 | B3: 1月目 | C3: 2月目 | D3: 3月目 | E3: 4月目 | F3: 5月目 | G3: 6月目 | H3: 7月目 | I3: 8月目 | J3: 9月目 | K3: 10月目 | L3: 11月目 | M3: 12月目 | N3: 年間
A4: 無料相談件数（件） | B4: =前提条件!$D$7*前提条件!$C$15 -> 2 | C4: =前提条件!$D$7*前提条件!$C$15 -> 2 | D4: =前提条件!$D$7*前提条件!$C$15 -> 2 | E4: =前提条件!$D$7*前提条件!$C$16 -> 3 | F4: =前提条件!$D$7*前提条件!$C$16 -> 3 | G4: =前提条件!$D$7*前提条件!$C$16 -> 3 | H4: =前提条件!$D$7*前提条件!$C$17 -> 4 | I4: =前提条件!$D$7*前提条件!$C$17 -> 4 | J4: =前提条件!$D$7*前提条件!$C$17 -> 4 | K4: =前提条件!$D$7*前提条件!$C$17 -> 4 | L4: =前提条件!$D$7*前提条件!$C$17 -> 4 | M4: =前提条件!$D$7*前提条件!$C$17 -> 4 | N4: =SUM(B4:M4) -> 39
A5: 業務診断 件数（件） | B5: =B4*前提条件!$D$8 -> 0.8 | C5: =C4*前提条件!$D$8 -> 0.8 | D5: =D4*前提条件!$D$8 -> 0.8 | E5: =E4*前提条件!$D$8 -> 1.2 | F5: =F4*前提条件!$D$8 -> 1.2 | G5: =G4*前提条件!$D$8 -> 1.2 | H5: =H4*前提条件!$D$8 -> 1.6 | I5: =I4*前提条件!$D$8 -> 1.6 | ... M5: =M4*前提条件!$D$8 -> 1.6 | N5: =SUM(B5:M5) -> 15.6
A6: プロジェクト 件数（件） | B6: 0 | C6: =B5*前提条件!$D$9 -> 0.4 | D6: =C5*前提条件!$D$9 -> 0.4 | E6: =D5*前提条件!$D$9 -> 0.4 | F6: =E5*前提条件!$D$9 -> 0.6 | G6: =F5*前提条件!$D$9 -> 0.6 | H6: =G5*前提条件!$D$9 -> 0.6 | I6: =H5*前提条件!$D$9 -> 0.8 | J6: =I5*前提条件!$D$9 -> 0.8 | ... M6: =L5*前提条件!$D$9 -> 0.8 | N6: =SUM(B6:M6) -> 7
A7: 顧問 新規獲得（件） | B7: 0 | C7: =B6*前提条件!$D$10 -> 0 | D7: =C6*前提条件!$D$10 -> 0.16 | E7: =D6*前提条件!$D$10 -> 0.16 | F7: =E6*前提条件!$D$10 -> 0.16 | G7: =F6*前提条件!$D$10 -> 0.24 | H7: =G6*前提条件!$D$10 -> 0.24 | I7: =H6*前提条件!$D$10 -> 0.24 | J7: =I6*前提条件!$D$10 -> 0.32 | ... M7: =L6*前提条件!$D$10 -> 0.32 | N7: =SUM(B7:M7) -> 2.48
A8: 顧問 稼働数（件・月末） | B8: =B7 -> 0 | C8: =B8*(1-前提条件!$D$11)+C7 -> 0 | D8: =C8*(1-前提条件!$D$11)+D7 -> 0.16 | E8: =D8*(1-前提条件!$D$11)+E7 -> 0.3152 | F8: =E8*(1-前提条件!$D$11)+F7 -> 0.465744 | G8: =F8*(1-前提条件!$D$11)+G7 -> 0.69177168 | H8: =G8*(1-前提条件!$D$11)+H7 -> 0.91101853 | I8: =H8*(1-前提条件!$D$11)+I7 -> 1.123688 | J8: =I8*(1-前提条件!$D$11)+J7 -> 1.4099773 | ... M8: =L8*(1-前提条件!$D$11)+M7 -> 2.2183362 | N8: =M8 -> 2.2183362
A9: 研修 実施回数（回） | B9: 0 | C9: 0 | D9: =前提条件!$D$12 -> 1 | E9: 0 | F9: 0 | G9: =前提条件!$D$12 -> 1 | H9: 0 | I9: 0 | J9: =前提条件!$D$12 -> 1 | K9: 0 | L9: 0 | M9: =前提条件!$D$12 -> 1 | N9: =SUM(B9:M9) -> 4
A10: 売上（万円）
A11: 業務診断 | B11: =B5*前提条件!$C$20 -> 32 | C11: =C5*前提条件!$C$20 -> 32 | D11: =D5*前提条件!$C$20 -> 32 | E11: =E5*前提条件!$C$20 -> 48 | F11: =F5*前提条件!$C$20 -> 48 | G11: =G5*前提条件!$C$20 -> 48 | H11: =H5*前提条件!$C$20 -> 64 | I11: =I5*前提条件!$C$20 -> 64 | ... M11: =M5*前提条件!$C$20 -> 64 | N11: =SUM(B11:M11) -> 624
A12: プロジェクト | B12: =B6*前提条件!$C$21 -> 0 | C12: =C6*前提条件!$C$21 -> 32 | D12: =D6*前提条件!$C$21 -> 32 | E12: =E6*前提条件!$C$21 -> 32 | F12: =F6*前提条件!$C$21 -> 48 | G12: =G6*前提条件!$C$21 -> 48 | H12: =H6*前提条件!$C$21 -> 48 | I12: =I6*前提条件!$C$21 -> 64 | ... M12: =M6*前提条件!$C$21 -> 64 | N12: =SUM(B12:M12) -> 560
A13: 顧問契約 | B13: =B8*前提条件!$C$22 -> 0 | C13: =C8*前提条件!$C$22 -> 0 | D13: =D8*前提条件!$C$22 -> 3.2 | E13: =E8*前提条件!$C$22 -> 6.304 | F13: =F8*前提条件!$C$22 -> 9.31488 | G13: =G8*前提条件!$C$22 -> 13.835434 | H13: =H8*前提条件!$C$22 -> 18.220371 | I13: =I8*前提条件!$C$22 -> 22.473759 | ... M13: =M8*前提条件!$C$22 -> 44.366725 | N13: =SUM(B13:M13) -> 218.80923
A14: 研修 | B14: =B9*前提条件!$C$23 -> 0 | C14: =C9*前提条件!$C$23 -> 0 | D14: =D9*前提条件!$C$23 -> 25 | E14: =E9*前提条件!$C$23 -> 0 | F14: =F9*前提条件!$C$23 -> 0 | G14: =G9*前提条件!$C$23 -> 25 | H14: =H9*前提条件!$C$23 -> 0 | I14: =I9*前提条件!$C$23 -> 0 | ... M14: =M9*前提条件!$C$23 -> 25 | N14: =SUM(B14:M14) -> 100
A15: 売上合計 | B15: =SUM(B11:B14) -> 32 | C15: =SUM(C11:C14) -> 64 | D15: =SUM(D11:D14) -> 92.2 | E15: =SUM(E11:E14) -> 86.304 | F15: =SUM(F11:F14) -> 105.31488 | G15: =SUM(G11:G14) -> 134.83543 | H15: =SUM(H11:H14) -> 130.22037 | I15: =SUM(I11:I14) -> 150.47376 | ... M15: =SUM(M11:M14) -> 197.36672 | N15: =SUM(B15:M15) -> 1502.8092
A16: コスト（万円）
A17: 固定費（ツール＋経費） | B17: =前提条件!$C$26+前提条件!$C$27 -> 10 | C17: =前提条件!$C$26+前提条件!$C$27 -> 10 | D17: =前提条件!$C$26+前提条件!$C$27 -> 10 | E17: =前提条件!$C$26+前提条件!$C$27 -> 10 | F17: =前提条件!$C$26+前提条件!$C$27 -> 10 | G17: =前提条件!$C$26+前提条件!$C$27 -> 10 | H17: =前提条件!$C$26+前提条件!$C$27 -> 10 | I17: =前提条件!$C$26+前提条件!$C$27 -> 10 | ... M17: =前提条件!$C$26+前提条件!$C$27 -> 10 | N17: =SUM(B17:M17) -> 120
A18: 変動費 | B18: =B15*前提条件!$C$28 -> 1.6 | C18: =C15*前提条件!$C$28 -> 3.2 | D18: =D15*前提条件!$C$28 -> 4.61 | E18: =E15*前提条件!$C$28 -> 4.3152 | F18: =F15*前提条件!$C$28 -> 5.265744 | G18: =G15*前提条件!$C$28 -> 6.7417717 | H18: =H15*前提条件!$C$28 -> 6.5110185 | I18: =I15*前提条件!$C$28 -> 7.523688 | ... M18: =M15*前提条件!$C$28 -> 9.8683362 | N18: =SUM(B18:M18) -> 75.140461
A19: コスト合計 | B19: =B17+B18 -> 11.6 | C19: =C17+C18 -> 13.2 | D19: =D17+D18 -> 14.61 | E19: =E17+E18 -> 14.3152 | F19: =F17+F18 -> 15.265744 | G19: =G17+G18 -> 16.741772 | H19: =H17+H18 -> 16.511019 | I19: =I17+I18 -> 17.523688 | ... M19: =M17+M18 -> 19.868336 | N19: =SUM(B19:M19) -> 195.14046
A20: 営業利益 | B20: =B15-B19 -> 20.4 | C20: =C15-C19 -> 50.8 | D20: =D15-D19 -> 77.59 | E20: =E15-E19 -> 71.9888 | F20: =F15-F19 -> 90.049136 | G20: =G15-G19 -> 118.09366 | H20: =H15-H19 -> 113.70935 | I20: =I15-I19 -> 132.95007 | ... M20: =M15-M19 -> 177.49839 | N20: =SUM(B20:M20) -> 1307.6688
A21: 累計営業利益 | B21: =B20 -> 20.4 | C21: =B21+C20 -> 71.2 | D21: =C21+D20 -> 148.79 | E21: =D21+E20 -> 220.7788 | F21: =E21+F20 -> 310.82794 | G21: =F21+G20 -> 428.9216 | H21: =G21+H20 -> 542.63095 | I21: =H21+I20 -> 675.58102 | J21: =I21+J20 -> 837.72059 | ... M21: =L21+M20 -> 1307.6688 | N21: =M21 -> 1307.6688

Sheet 月次_強気
A1: 月次計画 — 強気シナリオ（金額: 万円・税抜 / 件数: 期待値）
A3: 月 | B3: 1月目 | C3: 2月目 | D3: 3月目 | E3: 4月目 | F3: 5月目 | G3: 6月目 | H3: 7月目 | I3: 8月目 | J3: 9月目 | K3: 10月目 | L3: 11月目 | M3: 12月目 | N3: 年間
A4: 無料相談件数（件） | B4: =前提条件!$E$7*前提条件!$C$15 -> 3 | C4: =前提条件!$E$7*前提条件!$C$15 -> 3 | D4: =前提条件!$E$7*前提条件!$C$15 -> 3 | E4: =前提条件!$E$7*前提条件!$C$16 -> 4.5 | F4: =前提条件!$E$7*前提条件!$C$16 -> 4.5 | G4: =前提条件!$E$7*前提条件!$C$16 -> 4.5 | H4: =前提条件!$E$7*前提条件!$C$17 -> 6 | I4: =前提条件!$E$7*前提条件!$C$17 -> 6 | J4: =前提条件!$E$7*前提条件!$C$17 -> 6 | K4: =前提条件!$E$7*前提条件!$C$17 -> 6 | L4: =前提条件!$E$7*前提条件!$C$17 -> 6 | M4: =前提条件!$E$7*前提条件!$C$17 -> 6 | N4: =SUM(B4:M4) -> 58.5
A5: 業務診断 件数（件） | B5: =B4*前提条件!$E$8 -> 1.5 | C5: =C4*前提条件!$E$8 -> 1.5 | D5: =D4*前提条件!$E$8 -> 1.5 | E5: =E4*前提条件!$E$8 -> 2.25 | F5: =F4*前提条件!$E$8 -> 2.25 | G5: =G4*前提条件!$E$8 -> 2.25 | H5: =H4*前提条件!$E$8 -> 3 | I5: =I4*前提条件!$E$8 -> 3 | ... M5: =M4*前提条件!$E$8 -> 3 | N5: =SUM(B5:M5) -> 29.25
A6: プロジェクト 件数（件） | B6: 0 | C6: =B5*前提条件!$E$9 -> 0.9 | D6: =C5*前提条件!$E$9 -> 0.9 | E6: =D5*前提条件!$E$9 -> 0.9 | F6: =E5*前提条件!$E$9 -> 1.35 | G6: =F5*前提条件!$E$9 -> 1.35 | H6: =G5*前提条件!$E$9 -> 1.35 | I6: =H5*前提条件!$E$9 -> 1.8 | J6: =I5*前提条件!$E$9 -> 1.8 | ... M6: =L5*前提条件!$E$9 -> 1.8 | N6: =SUM(B6:M6) -> 15.75
A7: 顧問 新規獲得（件） | B7: 0 | C7: =B6*前提条件!$E$10 -> 0 | D7: =C6*前提条件!$E$10 -> 0.45 | E7: =D6*前提条件!$E$10 -> 0.45 | F7: =E6*前提条件!$E$10 -> 0.45 | G7: =F6*前提条件!$E$10 -> 0.675 | H7: =G6*前提条件!$E$10 -> 0.675 | I7: =H6*前提条件!$E$10 -> 0.675 | J7: =I6*前提条件!$E$10 -> 0.9 | ... M7: =L6*前提条件!$E$10 -> 0.9 | N7: =SUM(B7:M7) -> 6.975
A8: 顧問 稼働数（件・月末） | B8: =B7 -> 0 | C8: =B8*(1-前提条件!$E$11)+C7 -> 0 | D8: =C8*(1-前提条件!$E$11)+D7 -> 0.45 | E8: =D8*(1-前提条件!$E$11)+E7 -> 0.891 | F8: =E8*(1-前提条件!$E$11)+F7 -> 1.32318 | G8: =F8*(1-前提条件!$E$11)+G7 -> 1.9717164 | H8: =G8*(1-前提条件!$E$11)+H7 -> 2.6072821 | I8: =H8*(1-前提条件!$E$11)+I7 -> 3.2301364 | J8: =I8*(1-前提条件!$E$11)+J7 -> 4.0655337 | ... M8: =L8*(1-前提条件!$E$11)+M7 -> 6.4728078 | N8: =M8 -> 6.4728078
A9: 研修 実施回数（回） | B9: 0 | C9: 0 | D9: =前提条件!$E$12 -> 2 | E9: 0 | F9: 0 | G9: =前提条件!$E$12 -> 2 | H9: 0 | I9: 0 | J9: =前提条件!$E$12 -> 2 | K9: 0 | L9: 0 | M9: =前提条件!$E$12 -> 2 | N9: =SUM(B9:M9) -> 8
A10: 売上（万円）
A11: 業務診断 | B11: =B5*前提条件!$C$20 -> 60 | C11: =C5*前提条件!$C$20 -> 60 | D11: =D5*前提条件!$C$20 -> 60 | E11: =E5*前提条件!$C$20 -> 90 | F11: =F5*前提条件!$C$20 -> 90 | G11: =G5*前提条件!$C$20 -> 90 | H11: =H5*前提条件!$C$20 -> 120 | I11: =I5*前提条件!$C$20 -> 120 | ... M11: =M5*前提条件!$C$20 -> 120 | N11: =SUM(B11:M11) -> 1170
A12: プロジェクト | B12: =B6*前提条件!$C$21 -> 0 | C12: =C6*前提条件!$C$21 -> 72 | D12: =D6*前提条件!$C$21 -> 72 | E12: =E6*前提条件!$C$21 -> 72 | F12: =F6*前提条件!$C$21 -> 108 | G12: =G6*前提条件!$C$21 -> 108 | H12: =H6*前提条件!$C$21 -> 108 | I12: =I6*前提条件!$C$21 -> 144 | ... M12: =M6*前提条件!$C$21 -> 144 | N12: =SUM(B12:M12) -> 1260
A13: 顧問契約 | B13: =B8*前提条件!$C$22 -> 0 | C13: =C8*前提条件!$C$22 -> 0 | D13: =D8*前提条件!$C$22 -> 9 | E13: =E8*前提条件!$C$22 -> 17.82 | F13: =F8*前提条件!$C$22 -> 26.4636 | G13: =G8*前提条件!$C$22 -> 39.434328 | H13: =H8*前提条件!$C$22 -> 52.145641 | I13: =I8*前提条件!$C$22 -> 64.602729 | ... M13: =M8*前提条件!$C$22 -> 129.45616 | N13: =SUM(B13:M13) -> 631.64836
A14: 研修 | B14: =B9*前提条件!$C$23 -> 0 | C14: =C9*前提条件!$C$23 -> 0 | D14: =D9*前提条件!$C$23 -> 50 | E14: =E9*前提条件!$C$23 -> 0 | F14: =F9*前提条件!$C$23 -> 0 | G14: =G9*前提条件!$C$23 -> 50 | H14: =H9*前提条件!$C$23 -> 0 | I14: =I9*前提条件!$C$23 -> 0 | ... M14: =M9*前提条件!$C$23 -> 50 | N14: =SUM(B14:M14) -> 200
A15: 売上合計 | B15: =SUM(B11:B14) -> 60 | C15: =SUM(C11:C14) -> 132 | D15: =SUM(D11:D14) -> 191 | E15: =SUM(E11:E14) -> 179.82 | F15: =SUM(F11:F14) -> 224.4636 | G15: =SUM(G11:G14) -> 287.43433 | H15: =SUM(H11:H14) -> 280.14564 | I15: =SUM(I11:I14) -> 328.60273 | ... M15: =SUM(M11:M14) -> 443.45616 | N15: =SUM(B15:M15) -> 3261.6484
A16: コスト（万円）
A17: 固定費（ツール＋経費） | B17: =前提条件!$C$26+前提条件!$C$27 -> 10 | C17: =前提条件!$C$26+前提条件!$C$27 -> 10 | D17: =前提条件!$C$26+前提条件!$C$27 -> 10 | E17: =前提条件!$C$26+前提条件!$C$27 -> 10 | F17: =前提条件!$C$26+前提条件!$C$27 -> 10 | G17: =前提条件!$C$26+前提条件!$C$27 -> 10 | H17: =前提条件!$C$26+前提条件!$C$27 -> 10 | I17: =前提条件!$C$26+前提条件!$C$27 -> 10 | ... M17: =前提条件!$C$26+前提条件!$C$27 -> 10 | N17: =SUM(B17:M17) -> 120
A18: 変動費 | B18: =B15*前提条件!$C$28 -> 3 | C18: =C15*前提条件!$C$28 -> 6.6 | D18: =D15*前提条件!$C$28 -> 9.55 | E18: =E15*前提条件!$C$28 -> 8.991 | F18: =F15*前提条件!$C$28 -> 11.22318 | G18: =G15*前提条件!$C$28 -> 14.371716 | H18: =H15*前提条件!$C$28 -> 14.007282 | I18: =I15*前提条件!$C$28 -> 16.430136 | ... M18: =M15*前提条件!$C$28 -> 22.172808 | N18: =SUM(B18:M18) -> 163.08242
A19: コスト合計 | B19: =B17+B18 -> 13 | C19: =C17+C18 -> 16.6 | D19: =D17+D18 -> 19.55 | E19: =E17+E18 -> 18.991 | F19: =F17+F18 -> 21.22318 | G19: =G17+G18 -> 24.371716 | H19: =H17+H18 -> 24.007282 | I19: =I17+I18 -> 26.430136 | ... M19: =M17+M18 -> 32.172808 | N19: =SUM(B19:M19) -> 283.08242
A20: 営業利益 | B20: =B15-B19 -> 47 | C20: =C15-C19 -> 115.4 | D20: =D15-D19 -> 171.45 | E20: =E15-E19 -> 160.829 | F20: =F15-F19 -> 203.24042 | G20: =G15-G19 -> 263.06261 | H20: =H15-H19 -> 256.13836 | I20: =I15-I19 -> 302.17259 | ... M20: =M15-M19 -> 411.28335 | N20: =SUM(B20:M20) -> 2978.5659
A21: 累計営業利益 | B21: =B20 -> 47 | C21: =B21+C20 -> 162.4 | D21: =C21+D20 -> 333.85 | E21: =D21+E20 -> 494.679 | F21: =E21+F20 -> 697.91942 | G21: =F21+G20 -> 960.98203 | H21: =G21+H20 -> 1217.1204 | I21: =H21+I20 -> 1519.293 | J21: =I21+J20 -> 1884.8381 | ... M21: =L21+M20 -> 2978.5659 | N21: =M21 -> 2978.5659

Sheet シナリオ比較
B1: 初年度サマリー — シナリオ比較（万円・税抜）
B2: 緑字＝各月次シートの年間欄を参照。前提を変えると自動で更新されます。
C4: 保守 | D4: 標準 | E4: 強気
B5: 年間売上 合計 | C5: =月次_保守!N15 -> 448.77142 | D5: =月次_標準!N15 -> 1502.8092 | E5: =月次_強気!N15 -> 3261.6484
B6: うち 業務診断 | C6: =月次_保守!N11 -> 234 | D6: =月次_標準!N11 -> 624 | E6: =月次_強気!N11 -> 1170
B7: うち プロジェクト | C7: =月次_保守!N12 -> 168 | D7: =月次_標準!N12 -> 560 | E7: =月次_強気!N12 -> 1260
B8: うち 顧問契約 | C8: =月次_保守!N13 -> 46.771424 | D8: =月次_標準!N13 -> 218.80923 | E8: =月次_強気!N13 -> 631.64836
B9: うち 研修 | C9: =月次_保守!N14 -> 0 | D9: =月次_標準!N14 -> 100 | E9: =月次_強気!N14 -> 200
B10: 年間コスト 合計 | C10: =月次_保守!N19 -> 142.43857 | D10: =月次_標準!N19 -> 195.14046 | E10: =月次_強気!N19 -> 283.08242
B11: 年間営業利益 | C11: =月次_保守!N20 -> 306.33285 | D11: =月次_標準!N20 -> 1307.6688 | E11: =月次_強気!N20 -> 2978.5659
B12: 12月目の月次売上 | C12: =月次_保守!M15 -> 52.485715 | D12: =月次_標準!M15 -> 197.36672 | E12: =月次_強気!M15 -> 443.45616
B13: 年末の顧問稼働数（件） | C13: =月次_保守!N8 -> 0.46428573 | D13: =月次_標準!N8 -> 2.2183362 | E13: =月次_強気!N8 -> 6.4728078
B14: 年間の無料相談件数（件） | C14: =月次_保守!N4 -> 19.5 | D14: =月次_標準!N4 -> 39 | E14: =月次_強気!N4 -> 58.5
B16: ※ 役員報酬・税金・設立費用は含まない営業ベースの簡易モデル。件数は期待値（小数）。
B17: ※ 前提は全て仮置き。営業実績が出たら「前提条件」シートを実績値で更新すること。
